qctrlcoreworkflowmanager/__init__.py
qctrlcoreworkflowmanager/main.py
qctrl_core_workflow_manager-0.0.1a0.dist-info/METADATA
qctrl_core_workflow_manager-0.0.1a0.dist-info/WHEEL
qctrl_core_workflow_manager-0.0.1a0.dist-info/RECORD
